{"cameraPoint":{"x":0.0,"y":0.0},"animations":[{"prefix":"idle","offset":{"x":0,"y":-70},"looped":false,"flipX":false,"flipY":false,"name":"dance","frameRate":24},{"prefix":"left","offset":{"x":0,"y":-70},"looped":false,"flipX":false,"flipY":false,"name":"SingLEFT","frameRate":24},{"prefix":"down","offset":{"x":0,"y":-80},"looped":false,"flipX":false,"flipY":false,"name":"SingDOWN","frameRate":24},{"prefix":"up","offset":{"x":0,"y":-70},"looped":false,"flipX":false,"flipY":false,"name":"SingUP","frameRate":24},{"prefix":"right","offset":{"x":0,"y":-90},"looped":false,"flipX":false,"flipY":false,"name":"SingRIGHT","frameRate":24}],"healthColor":"0x006800","singDuration":8,"image":"gotta-sweep","format":"sparrow","danceEvery":2,"healthIcon":"gotta-sweep","flipX":false,"flipY":false,"antialiasing":false,"name":"gotta-sweep","danceSteps":["dance"],"scale":{"x":1.15,"y":1.15}}